SAMMEC2/GA.py
SAMMEC2/SAMMEC2.py
SAMMEC2/__init__.py
sklearn/__init__.py
sklearn/_config.py
sklearn/_distributor_init.py
sklearn/_min_dependencies.py
sklearn/base.py
sklearn/calibration.py
sklearn/conftest.py
sklearn/discriminant_analysis.py
sklearn/dummy.py
sklearn/exceptions.py
sklearn/isotonic.py
sklearn/kernel_approximation.py
sklearn/kernel_ridge.py
sklearn/multiclass.py
sklearn/multioutput.py
sklearn/naive_bayes.py
sklearn/pipeline.py
sklearn/random_projection.py
sklearn/__check_build/__init__.py
sklearn/_build_utils/__init__.py
sklearn/_build_utils/openmp_helpers.py
sklearn/_build_utils/pre_build_helpers.py
sklearn/_build_utils/tempita.py
sklearn/_build_utils/version.py
sklearn/_loss/__init__.py
sklearn/_loss/link.py
sklearn/_loss/loss.py
sklearn/_loss/tests/__init__.py
sklearn/_loss/tests/test_link.py
sklearn/_loss/tests/test_loss.py
sklearn/cluster/__init__.py
sklearn/cluster/_affinity_propagation.py
sklearn/cluster/_agglomerative.py
sklearn/cluster/_bicluster.py
sklearn/cluster/_birch.py
sklearn/cluster/_bisect_k_means.py
sklearn/cluster/_dbscan.py
sklearn/cluster/_feature_agglomeration.py
sklearn/cluster/_kmeans.py
sklearn/cluster/_mean_shift.py
sklearn/cluster/_optics.py
sklearn/cluster/_spectral.py
sklearn/cluster/_hdbscan/__init__.py
sklearn/cluster/_hdbscan/hdbscan.py
sklearn/cluster/_hdbscan/tests/__init__.py
sklearn/cluster/_hdbscan/tests/test_reachibility.py
sklearn/cluster/tests/__init__.py
sklearn/cluster/tests/common.py
sklearn/cluster/tests/test_affinity_propagation.py
sklearn/cluster/tests/test_bicluster.py
sklearn/cluster/tests/test_birch.py
sklearn/cluster/tests/test_bisect_k_means.py
sklearn/cluster/tests/test_dbscan.py
sklearn/cluster/tests/test_feature_agglomeration.py
sklearn/cluster/tests/test_hdbscan.py
sklearn/cluster/tests/test_hierarchical.py
sklearn/cluster/tests/test_k_means.py
sklearn/cluster/tests/test_mean_shift.py
sklearn/cluster/tests/test_optics.py
sklearn/cluster/tests/test_spectral.py
sklearn/compose/__init__.py
SAMMEC2-0.0.12.dist-info/METADATA
SAMMEC2-0.0.12.dist-info/WHEEL
SAMMEC2-0.0.12.dist-info/top_level.txt
SAMMEC2-0.0.12.dist-info/RECORD
